shimmer/__init__.py
shimmer/_client.py
shimmer/_process.py
shimmer/_protocol.py
pebble_shimmer-1.0.0a4.dist-info/METADATA
pebble_shimmer-1.0.0a4.dist-info/WHEEL
pebble_shimmer-1.0.0a4.dist-info/licenses/LICENSE
pebble_shimmer-1.0.0a4.dist-info/RECORD
