Metadata-Version: 2.4
Name: pebble-shimmer
Version: 1.0.0a4
Summary: A drop-in replacement for ops.pebble.Client that uses the Pebble CLI
Project-URL: Homepage, https://github.com/tonyandrewmeyer/shimmer
Project-URL: Repository, https://github.com/tonyandrewmeyer/shimmer
Project-URL: Documentation, https://github.com/tonyandrewmeyer/shimmer#readme
Project-URL: Bug Tracker, https://github.com/tonyandrewmeyer/shimmer/issues
Author-email: Tony Meyer <shimmer@aotearoa.dev>
License-File: LICENSE
Classifier: Development Status :: 3 - Alpha
Classifier: Intended Audience :: Developers
Classifier: License :: OSI Approved :: Apache Software License
Classifier: Operating System :: OS Independent
Classifier: Programming Language :: Python :: 3
Classifier: Programming Language :: Python :: 3.11
Classifier: Programming Language :: Python :: 3.12
Classifier: Programming Language :: Python :: 3.13
Classifier: Topic :: Software Development :: Libraries :: Python Modules
Classifier: Topic :: System :: Systems Administration
Requires-Python: >=3.11
Requires-Dist: ops<4,>=2.0.0
Requires-Dist: pyyaml>=6.0
Provides-Extra: dev
Requires-Dist: pre-commit>=3.0.0; extra == 'dev'
Requires-Dist: pytest-cov>=4.0.0; extra == 'dev'
Requires-Dist: pytest-mock>=3.10.0; extra == 'dev'
Requires-Dist: pytest>=7.0.0; extra == 'dev'
Requires-Dist: ruff>=0.1.0; extra == 'dev'
Requires-Dist: tox>=4.0.0; extra == 'dev'
Requires-Dist: ty; extra == 'dev'
